graphs/__init__.py
graphs/core.py
hitchhiker_graphs-0.2.0.dist-info/LICENSE
hitchhiker_graphs-0.2.0.dist-info/METADATA
hitchhiker_graphs-0.2.0.dist-info/WHEEL
hitchhiker_graphs-0.2.0.dist-info/RECORD
